punkeditor/__init__.py
punkeditor/__main__.py
punkeditor/command/__init__.py
punkeditor/command/edit_command.py
punkeditor/command/key_command.py
punkeditor/editbox.py
punkeditor-0.2.5.dist-info/METADATA
punkeditor-0.2.5.dist-info/WHEEL
punkeditor-0.2.5.dist-info/entry_points.txt
punkeditor-0.2.5.dist-info/RECORD
