Metadata-Version: 2.1
Name: punkeditor
Version: 0.2.5
Summary: Framework for flexible and powerful curses-based applications
License: MIT
Author: Steampunk Wizard
Author-email: punkeditor@steampunkwizard.ca
Requires-Python: >=3.11,<3.12
Classifier: License :: OSI Approved :: MIT License
Classifier: Programming Language :: Python :: 3
Classifier: Programming Language :: Python :: 3.11
Requires-Dist: wizlib (>=2.0.15,<3.0.0)
